<?xml version="1.0" encoding="utf-8" ?><dwsync><file name=".DS_Store" server="designannexe.com/kellymancini.com/html/" local="3473774553" remote="7768097296" Dst="-1" /><file name="black_arrow.png" server="designannexe.com/kellymancini.com/html/" local="3473774403" remote="-4611699243453529584" Dst="-1" /><file name="close.png" server="designannexe.com/kellymancini.com/html/" local="3473774403" remote="-4611699243453529584" Dst="-1" /><file name="directions.png" server="designannexe.com/kellymancini.com/html/" local="3473774403" remote="-4611699243453529584" Dst="-1" /><file name="facebook-axis.png" server="designannexe.com/kellymancini.com/html/" local="3473774405" remote="-4611699243453529584" Dst="-1" /><file name="h30.png" server="designannexe.com/kellymancini.com/html/" local="3473774405" remote="-4611699243453529584" Dst="-1" /><file name="google_map.png" server="designannexe.com/kellymancini.com/html/" local="3473774405" remote="-4611699243453529584" Dst="-1" /><file name="loading.gif" server="designannexe.com/kellymancini.com/html/" local="3473774406" remote="-4611699243453529584" Dst="-1" /><file name="transparent.png" server="designannexe.com/kellymancini.com/html/" local="3473774545" remote="7768097476" Dst="-1" /><file name="my_location_button_spinner.gif" server="designannexe.com/kellymancini.com/html/" local="3473774545" remote="7768097476" Dst="-1" /><file name="utilbuttons.png" server="designannexe.com/kellymancini.com/html/" local="3473774546" remote="7768097476" Dst="-1" /></dwsync>